Abstract_Exchange/CustomExchange.py
Abstract_Exchange/Exchanges.py
Abstract_Exchange/__init__.py
Abstract_Exchange/functions.py
Abstract_Exchange/loader.py
abstract_exchange-0.0.1.dist-info/LICENSE
abstract_exchange-0.0.1.dist-info/METADATA
abstract_exchange-0.0.1.dist-info/WHEEL
abstract_exchange-0.0.1.dist-info/top_level.txt
abstract_exchange-0.0.1.dist-info/RECORD
