Metadata-Version: 2.1
Name: abstract-exchange
Version: 0.0.1
Summary: UNKNOWN
Home-page: UNKNOWN
Author: Seyed Moala Takhtdar
Author-email: moallatakhtdar@gmail.com
License: MIT
Platform: UNKNOWN
Classifier: Programming Language :: Python :: 3
Classifier: License :: OSI Approved :: MIT License
Classifier: Operating System :: OS Independent
Requires-Dist: pybit (==2.0.0)
Requires-Dist: python-kucoin (==2.1.3)
Requires-Dist: ccxt (==1.76.12)
